yappt/__init__.py
yappt/grid.py
yappt/py.typed
yappt/tabulate.py
yappt/treeiter.py
yappt/util.py
yappt/types/__init__.py
yappt/types/column.py
yappt/types/duration.py
yappt/types/grid.py
yappt/types/prettyint.py
yappt-0.3.2.dist-info/LICENSE
yappt-0.3.2.dist-info/METADATA
yappt-0.3.2.dist-info/WHEEL
yappt-0.3.2.dist-info/top_level.txt
yappt-0.3.2.dist-info/RECORD
