Metadata-Version: 2.1
Name: yappt
Version: 0.3.2
Summary: Yet another pretty printer for tables and trees
Author-email: Paresh Adhia <padhia+github@gmail.com>
Project-URL: Homepage, https://github.com/padhia/yappt
Classifier: Programming Language :: Python :: 3
Requires-Python: >=3.9
License-File: LICENSE
Provides-Extra: tests
Requires-Dist: pytest ; extra == 'tests'
